getadpso/__init__.py
getadpso/getadpso.py
GetADPSO-0.2.dist-info/LICENSE
GetADPSO-0.2.dist-info/METADATA
GetADPSO-0.2.dist-info/WHEEL
GetADPSO-0.2.dist-info/entry_points.txt
GetADPSO-0.2.dist-info/top_level.txt
GetADPSO-0.2.dist-info/RECORD
