Metadata-Version: 2.1
Name: GetADPSO
Version: 0.2
Summary: A Python package to retrieve msDS-ResultantPSO and msDS-PSOApplied attributes from Active Directory.
Home-page: https://github.com/toncompte/getadpso
Author: WiseLife
Author-email: 
Classifier: Programming Language :: Python :: 3
Classifier: License :: OSI Approved :: GNU General Public License v3 (GPLv3)
Classifier: Operating System :: OS Independent
Requires-Python: >=3.6
License-File: LICENSE
Requires-Dist: ldap3
Requires-Dist: python-dateutil
Requires-Dist: pycryptodome
Requires-Dist: rich
Requires-Dist: setuptools
